{
  "project": {
    "id": "ld0o28",
    "name": "check-images",
    "creationTs": 1734131972015,
    "lastModifiedTs": 1734132036133,
    "userSetData": {
      "description": "",
      "tags": [],
      "contactURL": "",
      "tutorialYouTube": ""
    }
  },
  "graph": {
    "nodes": [
      {
        "id": "input_image_ledxjl",
        "nodeSpecId": "input_image",
        "customData": {
          "initialWidth": 448,
          "initialHeight": 240,
          "previewX": 16,
          "previewY": 16,
          "previewWidth": 448,
          "previewHeight": 304
        },
        "uiData": {
          "posX": -144,
          "posY": 64,
          "width": 176,
          "height": 180,
          "selected": true
        },
        "propValues": {
          "urls": [
            "https://storage.googleapis.com/tfweb/visualblocks-input-images/pic1.jpg",
            "https://storage.googleapis.com/tfweb/visualblocks-input-images/pic2.jpeg",
            "https://storage.googleapis.com/tfweb/visualblocks-input-images/pic3.jpg",
            "https://storage.googleapis.com/tfweb/visualblocks-input-images/pic4.jpeg",
            "https://storage.googleapis.com/tfweb/visualblocks-input-images/pic5.jpg",
            "https://storage.googleapis.com/tfweb/visualblocks-input-images/pic6.jpg",
            "https://storage.googleapis.com/tfweb/visualblocks-input-images/pic7.jpeg",
            "https://storage.googleapis.com/tfweb/visualblocks-input-images/pic8.jpg",
            "https://storage.googleapis.com/tfweb/visualblocks-input-images/pic9.jpg",
            "image=2p9mki",
            "image=nr136x"
          ],
          "gridColumnCount": 3,
          "allowUserUpload": true,
          "selectedImageUrl": "image=nr136x",
          "hidePreview": false
        }
      },
      {
        "id": "image_viewer_wg1vv9",
        "nodeSpecId": "image_viewer",
        "customData": {
          "previewX": 480,
          "previewY": 16,
          "previewWidth": 320,
          "previewHeight": 240
        },
        "uiData": {
          "posX": 128,
          "posY": 64,
          "width": 176,
          "height": 185,
          "selected": false
        },
        "propValues": {
          "columnCount": "2",
          "hidePreview": false
        },
        "inputValues": {
          "images": [],
          "urls": []
        },
        "incomingEdges": {
          "images": [
            {
              "sourceNodeId": "input_image_ledxjl",
              "outputId": "image"
            }
          ]
        }
      }
    ]
  },
  "customNodeUrls": [
    "https://raw.githubusercontent.com/sasinomalabs/donothing/refs/heads/main/1.js"
  ]
}